{"baseClass":"ElysiumDebugInternal","typeName":"ElysiumGraphs.ElysiumDebugInternal, ElysiumGraphs, Version=0.0.0.0, Culture=neutral, PublicKeyToken=null","fields":[],"methods":[{"name":"Log","methodClass":"ElysiumDebugInternal","fullName":"ElysiumGraphs.ElysiumDebugInternal, ElysiumGraphs, Version=0.0.0.0, Culture=neutral, PublicKeyToken=null","typeName":"","defaultReturnValue":{"name":"","type":"Void","order":-1,"parameterType":1},"parameters":[{"name":"format","type":"String","order":0,"parameterType":0}]},{"name":"LogWarning","methodClass":"ElysiumDebugInternal","fullName":"ElysiumGraphs.ElysiumDebugInternal, ElysiumGraphs, Version=0.0.0.0, Culture=neutral, PublicKeyToken=null","typeName":"","defaultReturnValue":{"name":"","type":"Void","order":-1,"parameterType":1},"parameters":[{"name":"format","type":"String","order":0,"parameterType":0}]},{"name":"LogError","methodClass":"ElysiumDebugInternal","fullName":"ElysiumGraphs.ElysiumDebugInternal, ElysiumGraphs, Version=0.0.0.0, Culture=neutral, PublicKeyToken=null","typeName":"","defaultReturnValue":{"name":"","type":"Void","order":-1,"parameterType":1},"parameters":[{"name":"format","type":"String","order":0,"parameterType":0}]},{"name":"LogAssert","methodClass":"ElysiumDebugInternal","fullName":"ElysiumGraphs.ElysiumDebugInternal, ElysiumGraphs, Version=0.0.0.0, Culture=neutral, PublicKeyToken=null","typeName":"","defaultReturnValue":{"name":"","type":"Void","order":-1,"parameterType":1},"parameters":[{"name":"format","type":"String","order":0,"parameterType":0}]}]}